release/__init__.py
release/gittools.py
release/main.py
tools/assisted_installer_stable_promotion.py
tools/check_ai_images.py
tools/consts.py
tools/custom_openshift_images.json
tools/github_prs_stats.py
tools/jira_cmd.py
tools/ocm-ai-update-issue-md
tools/release_tickets.py
tools/skopeo_utils.py
tools/trace_go_mod_dependencies.py
tools/triage_stats.py
tools/triage_status_report.py
tools/update_assisted_installer_yaml.py
tools/update_hash.py
tools/utils.py
tools/version_documentation.py
tools/fixtures/prow_job_statuses.json
tools/jira_client/__init__.py
tools/jira_client/consts.py
tools/jira_client/jira_api.py
tools/jira_client/jira_client_factory.py
tools/jira_client/jira_dryrun_client.py
tools/triage/__init__.py
tools/triage/add_triage_signature.py
tools/triage/attach_logs_in_jira.py
tools/triage/close_by_signature.py
tools/triage/common.py
tools/triage/create_triage_tickets.py
tools/triage/filters.py
tools/triage/triage_resolving_filters.json
tools/triage/ticket_search/__init__.py
tools/triage/ticket_search/action_extract_archive.py
tools/triage/ticket_search/action_grep.py
tools/triage/ticket_search/directory_cache.py
tools/triage/ticket_search/file_path_recursor.py
tools/triage/ticket_search/issue_cache.py
tools/triage/ticket_search/jira_attachment_downloader.py
tools/triage/ticket_search/settings.py
tools/triage/ticket_search/ticket_fetcher.py
tools/triage/ticket_search/ticket_parser.py
tools/triage/ticket_search/ticket_query.py
tools/triage/ticket_search/timer.py
tools/triage/ticket_search/triage_ticket.py
tools/triage/ticket_search/cli/__init__.py
tools/triage/ticket_search/cli/app.py
tools/triage/ticket_search/cli/command.py
tools/triage/ticket_search/cli/fetch_by_id.py
tools/triage/ticket_search/cli/generate_json_report.py
tools/triage/ticket_search/cli/search_by_path_and_content.py
tools/triage/ticket_search/cli/search_for_tickets.py
tools/triage/ticket_search/cli/workflow_data.py
tools/triage/utils/__init__.py
tools/triage/utils/extraction/__init__.py
assisted_ticket_search-2.22.1.dev4.dist-info/AUTHORS
assisted_ticket_search-2.22.1.dev4.dist-info/LICENSE
assisted_ticket_search-2.22.1.dev4.dist-info/METADATA
assisted_ticket_search-2.22.1.dev4.dist-info/WHEEL
assisted_ticket_search-2.22.1.dev4.dist-info/entry_points.txt
assisted_ticket_search-2.22.1.dev4.dist-info/pbr.json
assisted_ticket_search-2.22.1.dev4.dist-info/top_level.txt
assisted_ticket_search-2.22.1.dev4.dist-info/RECORD
