Metadata-Version: 2.1
Name: assisted-ticket-search
Version: 2.22.1.dev4
Summary: A temporary package for testing
Home-page: https://github.com/openshift-assisted/assisted-installer-deployment
Author: Nir Magnezi
Author-email: nmagnezi@redhat.com
License: Apache-2
License-File: LICENSE
License-File: AUTHORS
Requires-Dist: setuptools
Requires-Dist: async-timeout (==4.0.2)
Requires-Dist: attrs (==22.2.0)
Requires-Dist: cachecontrol[redis] (==0.12.11)
Requires-Dist: certifi (==2022.12.7)
Requires-Dist: cffi (==1.15.1)
Requires-Dist: charset-normalizer (==2.0.12)
Requires-Dist: colorlog (==4.7.2)
Requires-Dist: decorator (==4.4.2)
Requires-Dist: defusedxml (==0.7.1)
Requires-Dist: deprecated (==1.2.13)
Requires-Dist: fuzzywuzzy (==0.18.0)
Requires-Dist: idna (==3.4)
Requires-Dist: iniconfig (==2.0.0)
Requires-Dist: insights-core (==3.1.4)
Requires-Dist: jinja2 (==3.1.2)
Requires-Dist: jira (==3.4.1)
Requires-Dist: lockfile (==0.12.2)
Requires-Dist: markupsafe (==2.1.2)
Requires-Dist: msgpack (==1.0.4)
Requires-Dist: multi-key-dict (==2.0.3)
Requires-Dist: nestedarchive (==0.2.4)
Requires-Dist: networkx (==2.5.1)
Requires-Dist: oauthlib (==3.2.2)
Requires-Dist: packaging (==21.0)
Requires-Dist: pbr (==5.11.1)
Requires-Dist: pluggy (==1.0.0)
Requires-Dist: py (==1.11.0)
Requires-Dist: pycparser (==2.21)
Requires-Dist: pyfakefs (==5.1.0)
Requires-Dist: pygithub (==1.55)
Requires-Dist: pyjwt (==2.6.0)
Requires-Dist: pynacl (==1.5.0)
Requires-Dist: pyparsing (==3.0.9)
Requires-Dist: pytest (==7.1.1)
Requires-Dist: python-dateutil (==2.8.2)
Requires-Dist: python-gitlab (==2.10.1)
Requires-Dist: python-jenkins (==1.7.0)
Requires-Dist: python-levenshtein (==0.12.2)
Requires-Dist: pyyaml (==6.0)
Requires-Dist: redis (==4.4.2)
Requires-Dist: requests (==2.26.0)
Requires-Dist: requests-oauthlib (==1.3.1)
Requires-Dist: requests-toolbelt (==0.10.1)
Requires-Dist: retry (==0.9.2)
Requires-Dist: ruamel-yaml (==0.17.16)
Requires-Dist: six (==1.16.0)
Requires-Dist: slack-sdk (==3.19.2)
Requires-Dist: tabulate (==0.8.9)
Requires-Dist: tomli (==2.0.1)
Requires-Dist: tqdm (==4.59.0)
Requires-Dist: typing-extensions (==4.5.0)
Requires-Dist: urllib3 (==1.26.14)
Requires-Dist: wrapt (==1.14.1)
